smtp_test_server/__init__.py
smtp_test_server/context.py
smtp_test_server/exceptions.py
smtp_test_server/mock.py
smtp_test_server/net.py
smtp_test_server-0.1.0.dist-info/LICENSE.txt
smtp_test_server-0.1.0.dist-info/METADATA
smtp_test_server-0.1.0.dist-info/WHEEL
smtp_test_server-0.1.0.dist-info/RECORD
