Metadata-Version: 2.1
Name: smtp-test-server
Version: 0.1.0
Summary: Simple SMTP test server for running unit and integration tests.
Home-page: https://git.codebau.dev/jed/smtp-test-server
License: MIT
Keywords: test,unittest,integrationtest,mail,smtp,mock
Author: Juergen Edelbluth
Author-email: smtp-test-server@jued.de
Requires-Python: >=3.11,<4.0
Classifier: Development Status :: 2 - Pre-Alpha
Classifier: Environment :: Console
Classifier: Intended Audience :: Developers
Classifier: License :: OSI Approved :: MIT License
Classifier: Operating System :: MacOS :: MacOS X
Classifier: Operating System :: Microsoft :: Windows
Classifier: Operating System :: POSIX
Classifier: Programming Language :: Python :: 3
Classifier: Programming Language :: Python :: 3.11
Classifier: Programming Language :: Python :: 3.12
Classifier: Topic :: Software Development :: Quality Assurance
Classifier: Topic :: Software Development :: Testing
Classifier: Topic :: Utilities
Requires-Dist: aiosmtpd (>=1.4.4.post2,<2.0.0)
Project-URL: Changelog, https://git.codebau.dev/jed/smtp-test-server/CHANGELOG.md
Project-URL: Documentation, https://git.codebau.dev/jed/smtp-test-server
Project-URL: Issue Tracker, https://git.codebau.dev/jed/smtp-test-server/issues
Project-URL: Repository, https://git.codebau.dev/jed/smtp-test-server
Project-URL: Releases, https://git.codebau.dev/jed/smtp-test-server/releases
Project-URL: Wiki, https://git.codebau.dev/jed/smtp-test-server/wiki
